{
    "enabled": true,
    "neededInstalledMods": [],
    "neededUninstalledMods": [],
    "spawns": [
        {
            "id": "dragonair-tfc-1",
            "pokemon": "dragonair",
            "presets": [
                "seasonal"
            ],
            "type": "pokemon",
            "context": "grounded",
            "bucket": "rare",
            "level": "30-55",
            "weight": 10.0,
            "condition": {                
                "canSeeSky": true,
                "biomes": [
                    "#tfc:oceans"
                ]
            }
        }
    ]
}